pycute/__init__.py
pycute/cute.py
pycute/simulations.py
pycute/tent.py
pycute/utils.py
pycute-0.1.0.dist-info/LICENSE
pycute-0.1.0.dist-info/METADATA
pycute-0.1.0.dist-info/WHEEL
pycute-0.1.0.dist-info/top_level.txt
pycute-0.1.0.dist-info/RECORD
