Metadata-Version: 2.1
Name: pycute
Version: 0.1.0
Summary: Information-Theoretic Causal Inference on Event Sequences
Home-page: https://github.com/kailashbuki/pycute
Author: Kailash Budhathoki
Author-email: kailash.buki@gmail.com
License: MIT License
Platform: UNKNOWN
Classifier: Development Status :: 4 - Beta
Classifier: Intended Audience :: Science/Research
Classifier: Topic :: Software Development :: Libraries :: Python Modules
Classifier: License :: OSI Approved :: MIT License
Classifier: Programming Language :: Python :: 3
Classifier: Operating System :: OS Independent
Requires-Python: >=3.7
Requires-Dist: tqdm
Requires-Dist: pandas
Requires-Dist: numpy
Requires-Dist: pytest
